os_collect_config/__init__.py
os_collect_config/cache.py
os_collect_config/cfn.py
os_collect_config/collect.py
os_collect_config/common.py
os_collect_config/config_drive.py
os_collect_config/ec2.py
os_collect_config/exc.py
os_collect_config/heat.py
os_collect_config/heat_local.py
os_collect_config/keystone.py
os_collect_config/local.py
os_collect_config/merger.py
os_collect_config/request.py
os_collect_config/version.py
os_collect_config/zaqar.py
os_collect_config/tests/__init__.py
os_collect_config/tests/test_cache.py
os_collect_config/tests/test_cfn.py
os_collect_config/tests/test_collect.py
os_collect_config/tests/test_config_drive.py
os_collect_config/tests/test_ec2.py
os_collect_config/tests/test_heat.py
os_collect_config/tests/test_heat_local.py
os_collect_config/tests/test_keystone.py
os_collect_config/tests/test_local.py
os_collect_config/tests/test_merger.py
os_collect_config/tests/test_request.py
os_collect_config/tests/test_zaqar.py
os_collect_config-14.0.1.dist-info/AUTHORS
os_collect_config-14.0.1.dist-info/LICENSE
os_collect_config-14.0.1.dist-info/METADATA
os_collect_config-14.0.1.dist-info/WHEEL
os_collect_config-14.0.1.dist-info/entry_points.txt
os_collect_config-14.0.1.dist-info/pbr.json
os_collect_config-14.0.1.dist-info/top_level.txt
os_collect_config-14.0.1.dist-info/RECORD
