Metadata-Version: 2.1
Name: os-collect-config
Version: 14.0.1
Summary: Collect and cache metadata, run hooks on changes.
Home-page: https://opendev.org/openstack/os-collect-config
Author: OpenStack
Author-email: openstack-discuss@lists.openstack.org
Classifier: Development Status :: 4 - Beta
Classifier: Environment :: Console
Classifier: Environment :: OpenStack
Classifier: Intended Audience :: Developers
Classifier: Intended Audience :: Information Technology
Classifier: License :: OSI Approved :: Apache Software License
Classifier: Operating System :: OS Independent
Classifier: Programming Language :: Python
Classifier: Programming Language :: Python :: 3
Classifier: Programming Language :: Python :: 3 :: Only
Classifier: Programming Language :: Python :: 3.8
Classifier: Programming Language :: Python :: 3.9
Classifier: Programming Language :: Python :: 3.10
Classifier: Programming Language :: Python :: 3.11
Classifier: Programming Language :: Python :: 3.12
Requires-Python: >=3.8
License-File: LICENSE
License-File: AUTHORS
Requires-Dist: pbr >=2.0.0
Requires-Dist: python-keystoneclient >=3.8.0
Requires-Dist: python-heatclient >=1.10.0
Requires-Dist: python-zaqarclient >=1.0.0
Requires-Dist: requests >=2.14.2
Requires-Dist: lxml >=3.4.1
Requires-Dist: oslo.config >=5.2.0
Requires-Dist: oslo.log >=3.36.0
Requires-Dist: dogpile.cache >=0.6.2
